{
  "id": "kun-chick",
  "displayName": "Kun Chick",
  "description": "A tiny pixel-style chick inspired by a basketball stage meme, carrying a basketball as a Codex pet.",
  "spritesheetPath": "spritesheet.webp",
  "kind": null,
  "version": "1.0.0",
  "animations": {
    "focus": {
      "row": 11,
      "frames": 4,
      "frameDurations": [
        300,
        300,
        300,
        300
      ]
    },
    "merit": {
      "row": 9,
      "frames": 4,
      "frameDurations": [
        150,
        150,
        150,
        150
      ]
    },
    "music": {
      "row": 10,
      "frames": 8,
      "frameDurations": [
        140,
        140,
        140,
        140,
        140,
        140,
        140,
        140
      ]
    }
  }
}
